simple_bson/__init__.py
simple_bson/decoder.py
simple_bson/encoder.py
simple_bson/etc.py
simple_bson-0.0.2.dist-info/LICENSE
simple_bson-0.0.2.dist-info/WHEEL
simple_bson-0.0.2.dist-info/METADATA
simple_bson-0.0.2.dist-info/RECORD
