Metadata-Version: 2.1
Name: simple-bson
Version: 0.0.2
Summary: Python Bson Compatible Library
Home-page: https://github.com/DeltaLaboratory/simple-bson
Author: DeltaLaboratory
Author-email: delta@deltalab.dev
Requires-Python: >=3.6,<4.0
Classifier: Programming Language :: Python :: 3
Classifier: Programming Language :: Python :: 3.10
Classifier: Programming Language :: Python :: 3.6
Classifier: Programming Language :: Python :: 3.7
Classifier: Programming Language :: Python :: 3.8
Classifier: Programming Language :: Python :: 3.9
Project-URL: Repository, https://github.com/DeltaLaboratory/simple-bson
